{"translation":{"id":"HINIRV","language":"hin","name":"पवित्र बाइबिल","englishName":"Hindi Indian Revised Version Bible","licenseUrl":"https://ebible.org/Scriptures/details.php?id=hin2017","website":"https://ebible.org/Scriptures/details.php?id=hin2017","shortName":"IRV","availableFormats":["json"],"listOfBooksApiLink":"/api/HINIRV/books.json"},"book":{"id":"REV","name":"प्रकाशितवाक्य","commonName":"प्रकाशितवाक्य","title":"Revelation प्रकाशितवाक्य","firstChapterApiLink":"/api/HINIRV/प्रकाशितवाक्य/1.json","lastChapterApiLink":"/api/HINIRV/प्रकाशितवाक्य/22.json","numberOfChapters":22},"nextChapterApiLink":"/api/HINIRV/प्रकाशितवाक्य/6.json","previousChapterApiLink":"/api/HINIRV/प्रकाशितवाक्य/4.json","chapter":{"number":5,"content":[{"type":"heading","content":["मुहरबन्द पुस्तक कौन खोल सकता है?"]},{"type":"line_break"},{"type":"verse","number":1,"content":[{"text":"और जो सिंहासन पर बैठा था, मैंने उसके दाहिने हाथ में एक पुस्तक देखी, जो भीतर और बाहर लिखी हुई थी, और वह सात मुहर लगाकर बन्द की गई थी। (यहे. 2:9-10)","poem":1}]},{"type":"verse","number":2,"content":[{"text":"फिर मैंने एक बलवन्त स्वर्गदूत को देखा जो ऊँचे शब्द से यह प्रचार करता था “इस पुस्तक के खोलने और उसकी मुहरें तोड़ने के योग्य कौन है?”","poem":1}]},{"type":"verse","number":3,"content":[{"text":"और न स्वर्ग में*, न पृथ्वी पर, न पृथ्वी के नीचे कोई उस पुस्तक को खोलने या उस पर दृष्टि डालने के योग्य निकला*।","poem":1}]},{"type":"verse","number":4,"content":[{"text":"तब मैं फूट-फूटकर रोने लगा, क्योंकि उस पुस्तक के खोलने, या उस पर दृष्टि करने के योग्य कोई न मिला।","poem":1}]},{"type":"verse","number":5,"content":[{"text":"इस पर उन प्राचीनों में से एक ने मुझसे कहा, “मत रो; देख, यहूदा के गोत्र का वह सिंह, जो दाऊद का मूल है, उस पुस्तक को खोलने और उसकी सातों मुहरें तोड़ने के लिये जयवन्त हुआ है।” (उत्प. 49:9, यशा. 11:1, यशा. 11:10)*","poem":1}]},{"type":"verse","number":6,"content":[{"text":"तब मैंने उस सिंहासन और चारों प्राणियों और उन प्राचीनों के बीच में, मानो एक वध किया हुआ मेम्‍ना खड़ा देखा; उसके सात सींग और सात आँखें थीं; ये परमेश्‍वर की सातों आत्माएँ हैं, जो सारी पृथ्वी पर भेजी गई हैं। (जक. 4:10)","poem":1}]},{"type":"verse","number":7,"content":[{"text":"उसने आकर उसके दाहिने हाथ से जो सिंहासन पर बैठा था, वह पुस्तक ले ली, (प्रका. 5:1)","poem":1}]},{"type":"verse","number":8,"content":[{"text":"जब उसने पुस्तक ले ली, तो वे चारों प्राणी और चौबीसों प्राचीन उस मेम्‍ने के सामने गिर पड़े; और हर एक के हाथ में वीणा और धूप से भरे हुए सोने के कटोरे थे, ये तो पवित्र लोगों की प्रार्थनाएँ हैं। (प्रका. 5:14, प्रका. 19:4)","poem":1}]},{"type":"verse","number":9,"content":[{"text":"और वे यह नया गीत गाने लगे,","poem":1},{"text":"“तू इस पुस्तक के लेने, और उसकी मुहरें खोलने के योग्य है;","poem":1},{"text":"क्योंकि तूने वध होकर अपने लहू से हर एक कुल, और भाषा, और लोग, और जाति में से","poem":1},{"text":"परमेश्‍वर के लिये लोगों को मोल लिया है। (प्रका. 5:12)","poem":1}]},{"type":"verse","number":10,"content":[{"text":"“और उन्हें हमारे परमेश्‍वर के लिये एक राज्य और याजक बनाया; और वे पृथ्वी पर राज्य करते हैं।” (प्रका. 1:6)","poem":1}]},{"type":"heading","content":["स्वर्गदूतों द्वारा मेम्‍ने की प्रशंसा"]},{"type":"line_break"},{"type":"verse","number":11,"content":[{"text":"जब मैंने देखा, तो उस सिंहासन और उन प्राणियों और उन प्राचीनों के चारों ओर बहुत से स्वर्गदूतों का शब्द सुना, जिनकी गिनती लाखों और करोड़ों की थी। (दानि. 7:10)","poem":1}]},{"type":"verse","number":12,"content":[{"text":"और वे ऊँचे शब्द से कहते थे, “वध किया हुआ मेम्‍ना ही सामर्थ्य, और धन, और ज्ञान, और शक्ति, और आदर, और महिमा, और स्तुति के योग्य है*।” (प्रका. 5:9)","poem":1}]},{"type":"line_break"},{"type":"verse","number":13,"content":[{"text":"फिर मैंने स्वर्ग में, और पृथ्वी पर, और पृथ्वी के नीचे, और समुद्र की सब रची हुई वस्तुओं को, और सब कुछ को जो उनमें हैं, यह कहते सुना, “जो सिंहासन पर बैठा है, उसकी, और मेम्‍ने की स्तुति, और आदर, और महिमा, और राज्य, युगानुयुग रहे।”","poem":1}]},{"type":"verse","number":14,"content":[{"text":"और चारों प्राणियों ने आमीन कहा, और प्राचीनों ने गिरकर दण्डवत् किया।","poem":1}]}],"footnotes":[]}}