{"translation":{"id":"GRCBRE","language":"grc","name":"μετάφραση των εβδομήκοντα","englishName":"Brenton Septuagint","licenseUrl":"https://ebible.org/Scriptures/details.php?id=grcbrent","website":"https://ebible.org/Scriptures/details.php?id=grcbrent","shortName":"BRE","availableFormats":["json"],"listOfBooksApiLink":"/api/GRCBRE/books.json","textDirection":"ltr"},"book":{"id":"PSA","name":"ΨΑΛΜΟΙ","commonName":"ΨΑΛΜΟΙ","title":"ΨΑΛΜΟΙ","firstChapterApiLink":"/api/GRCBRE/ΨΑΛΜΟΙ/1.json","lastChapterApiLink":"/api/GRCBRE/ΨΑΛΜΟΙ/151.json","numberOfChapters":151},"nextChapterApiLink":"/api/GRCBRE/ΨΑΛΜΟΙ/47.json","previousChapterApiLink":"/api/GRCBRE/ΨΑΛΜΟΙ/45.json","chapter":{"number":46,"content":[{"type":"hebrew_subtitle","content":[]},{"type":"verse","number":1,"content":["Εἰς τὸ τέλος, ὑπὲρ τῶν υἱῶν Κορὲ ψαλμός."]},{"type":"line_break"},{"type":"verse","number":2,"content":["Παντὰ τὰ ἔθνη κροτήσατε χεῖρας, ἀλαλάξατε τῷ Θεῷ ἐν φωνῇ ἀγαλλιάσεως."]},{"type":"verse","number":3,"content":["Ὅτι Κύριος ὕψιστος, φοβερὸς, βασιλεὺς μέγας ἐπὶ πᾶσαν τὴν γῆν."]},{"type":"verse","number":4,"content":["Ὑπέταξε λαοὺς ἡμῖν, καὶ ἔθνη ὑπὸ τοὺς πόδας ἡμῶν·"]},{"type":"verse","number":5,"content":["Ἐξελέξατο ἡμῖν τὴν κληρονομίαν αὐτοῦ, τὴν καλλονὴν Ἰακὼβ, ἣν ἠγάπησε· διάψαλμα."]},{"type":"line_break"},{"type":"verse","number":6,"content":["Ἀνέβη ὁ Θεὸς ἐν ἀλαλαγμῷ, Κύριος ἐν φωνῇ σάλπιγγος."]},{"type":"verse","number":7,"content":["Ψάλατε τῷ Θεῷ ἡμῶν, ψάλατε· ψάλατε τῷ βασιλεῖ ἡμῶν, ψάλατε."]},{"type":"verse","number":8,"content":["Ὅτι βασιλεὺς πάσης τῆς γῆς ὁ Θεὸς, ψάλατε συνετῶς."]},{"type":"verse","number":9,"content":["Ἐβασίλευσεν ὁ Θεὸς ἐπὶ τὰ ἔθνη, ὁ Θεὸς κάθηται ἐπὶ θρόνου ἁγίου αὐτοῦ."]},{"type":"verse","number":10,"content":["Ἄρχοντες λαῶν συνήχθησαν μετὰ τοῦ Θεοῦ Ἀβραὰμ, ὅτι τοῦ Θεοῦ οἱ κραταιοὶ τῆς γῆς σφόδρα ἐπῄρθησαν."]}],"footnotes":[]}}