{"translation":{"id":"ARBNAV","name":"كتاب الحياة","englishName":"New Arabic Version (Ketab El Hayat) Book of Life","shortName":"NAV","language":"arb","licenseUrl":"https://ebible.org/find/details.php?id=arbnav","website":"https://ebible.org/arbnav/","availableFormats":["json"],"listOfBooksApiLink":"/api/ARBNAV/books.json","textDirection":"rtl"},"book":{"id":"PSA","name":"مزمور","commonName":"المَزامِير","title":"كِتابُ المَزامِير","firstChapterApiLink":"/api/ARBNAV/المَزامِير/1.json","lastChapterApiLink":"/api/ARBNAV/المَزامِير/150.json","numberOfChapters":150},"nextChapterApiLink":"/api/ARBNAV/المَزامِير/123.json","previousChapterApiLink":"/api/ARBNAV/المَزامِير/121.json","chapter":{"number":122,"content":[{"type":"line_break"},{"type":"verse","number":1,"content":["فَرِحْتُ بِالْقَائِلِينَ لِي: لِنَذْهَبْ مَعاً إِلَى بَيْتِ الرَّبِّ."]},{"type":"verse","number":2,"content":["تَقِفُ أَقْدَامُنَا الآنَ دَاخِلَ أَبْوَابِكِ يَاأُورُشَلِيمُ."]},{"type":"verse","number":3,"content":["أُورُشَلِيمُ الْمَبْنِيَّةُ كَمَدِينَةٍ مُتَمَاسِكَةٍ مُتَّحِدَةٍ."]},{"type":"verse","number":4,"content":["إِلَيْهَا صَعِدَتِ الأَسْبَاطُ، أَسْبَاطُ الرَّبِّ لِتَرْفَعَ الشُّكْرَ لَهُ بِحَسَبِ أَوَامِرِهِ."]},{"type":"verse","number":5,"content":["هُنَاكَ نُصِبَتْ عُرُوشُ الْقَضَاءِ، عُرُوشُ آلِ دَاوُدَ."]},{"type":"verse","number":6,"content":["صَلُّوا لأَجْلِ سَلاَمِ أُورُشَلِيمَ. لِيُفْلِحْ مُحِبُّوكِ وَيَطْمَئِنُّوا."]},{"type":"verse","number":7,"content":["لِيَكُنِ السَّلاَمُ دَاخِلَ أَسْوَارِكِ، وَالأَمَانُ دَاخِلَ قُصُورِكِ."]},{"type":"verse","number":8,"content":["مِنْ أَجْلِ إِخْوَتِي وَأَصْحَابِي أَقُولُ: لِيَسُدْ فِيكِ سَلاَمٌ."]},{"type":"verse","number":9,"content":["مِنْ أَجْلِ الرَّبِّ إِلَهِنَا أَلْتَمِسُ لَكِ خَيْراً."]}],"footnotes":[]}}